dsc_sdk/__init__.py
dsc_sdk/api.py
dsc_sdk/constants.py
dsc_sdk/erc_constants.py
dsc_sdk/exceptions.py
dsc_sdk/number_helpers.py
dsc_sdk/special.py
dsc_sdk/test_api.py
dsc_sdk/test_number_helpers.py
dsc_sdk/test_transaction.py
dsc_sdk/test_types.py
dsc_sdk/test_wallet.py
dsc_sdk/transaction.py
dsc_sdk/tx_types.py
dsc_sdk/wallet.py
dsc_sdk/proto/__init__.py
dsc_sdk/proto/cosmos/__init__.py
dsc_sdk/proto/cosmos/auth/__init__.py
dsc_sdk/proto/cosmos/auth/v1beta1/__init__.py
dsc_sdk/proto/cosmos/auth/v1beta1/auth_pb2.py
dsc_sdk/proto/cosmos/auth/v1beta1/genesis_pb2.py
dsc_sdk/proto/cosmos/auth/v1beta1/query_pb2.py
dsc_sdk/proto/cosmos/authz/__init__.py
dsc_sdk/proto/cosmos/authz/v1beta1/__init__.py
dsc_sdk/proto/cosmos/authz/v1beta1/authz_pb2.py
dsc_sdk/proto/cosmos/authz/v1beta1/event_pb2.py
dsc_sdk/proto/cosmos/authz/v1beta1/genesis_pb2.py
dsc_sdk/proto/cosmos/authz/v1beta1/query_pb2.py
dsc_sdk/proto/cosmos/authz/v1beta1/tx_pb2.py
dsc_sdk/proto/cosmos/bank/__init__.py
dsc_sdk/proto/cosmos/bank/v1beta1/__init__.py
dsc_sdk/proto/cosmos/bank/v1beta1/authz_pb2.py
dsc_sdk/proto/cosmos/bank/v1beta1/bank_pb2.py
dsc_sdk/proto/cosmos/bank/v1beta1/genesis_pb2.py
dsc_sdk/proto/cosmos/bank/v1beta1/query_pb2.py
dsc_sdk/proto/cosmos/bank/v1beta1/tx_pb2.py
dsc_sdk/proto/cosmos/base/__init__.py
dsc_sdk/proto/cosmos/base/abci/__init__.py
dsc_sdk/proto/cosmos/base/abci/v1beta1/__init__.py
dsc_sdk/proto/cosmos/base/abci/v1beta1/abci_pb2.py
dsc_sdk/proto/cosmos/base/kv/__init__.py
dsc_sdk/proto/cosmos/base/kv/v1beta1/__init__.py
dsc_sdk/proto/cosmos/base/kv/v1beta1/kv_pb2.py
dsc_sdk/proto/cosmos/base/query/__init__.py
dsc_sdk/proto/cosmos/base/query/v1beta1/__init__.py
dsc_sdk/proto/cosmos/base/query/v1beta1/pagination_pb2.py
dsc_sdk/proto/cosmos/base/reflection/__init__.py
dsc_sdk/proto/cosmos/base/reflection/v1beta1/__init__.py
dsc_sdk/proto/cosmos/base/reflection/v1beta1/reflection_pb2.py
dsc_sdk/proto/cosmos/base/reflection/v2alpha1/__init__.py
dsc_python_sdk-1.1.9.dist-info/METADATA
dsc_python_sdk-1.1.9.dist-info/WHEEL
dsc_python_sdk-1.1.9.dist-info/top_level.txt
dsc_python_sdk-1.1.9.dist-info/RECORD
