Metadata-Version: 2.1
Name: dsc-python-sdk
Version: 1.1.9
Summary: UNKNOWN
Home-page: https://bitbucket.org/decimalteam/dsc-python-sdk
Author: DecimalTeam
License: UNKNOWN
Platform: UNKNOWN
Classifier: Programming Language :: Python :: 3
Classifier: License :: OSI Approved :: MIT License
Classifier: Operating System :: OS Independent
Requires-Python: >=3.6
Requires-Dist: asn1crypto (==1.5.1)
Requires-Dist: base58 (==2.0.0)
Requires-Dist: base58check (==1.0.2)
Requires-Dist: bech32 (==1.2.0)
Requires-Dist: bip32 (==3.3)
Requires-Dist: cached-property (==1.5.2)
Requires-Dist: cffi (==1.14.3)
Requires-Dist: chardet (==3.0.4)
Requires-Dist: coincurve (==17.0.0)
Requires-Dist: ecdsa (==0.16.1)
Requires-Dist: eth-hash (==0.3.1)
Requires-Dist: eth-typing (==2.2.2)
Requires-Dist: eth-utils (==1.10.0)
Requires-Dist: ethereum (==2.3.2)
Requires-Dist: future (==0.18.2)
Requires-Dist: idna (==2.10)
Requires-Dist: mnemonic (==0.20)
Requires-Dist: mypy-extensions (==0.4.3)
Requires-Dist: pbkdf2 (==1.3)
Requires-Dist: py-ecc (==5.1.0)
Requires-Dist: pyaes (==1.6.1)
Requires-Dist: pycparser (==2.20)
Requires-Dist: pycryptodome (==3.15.0)
Requires-Dist: pycryptodomex (==3.15.0)
Requires-Dist: pyethash (==0.1.27)
Requires-Dist: requests (==2.25.0)
Requires-Dist: protobuf (==3.19.5)
Requires-Dist: web3 (==5.31.1)
